pywsi/__init__.py
pywsi/exceptions.py
pywsi/filters.py
pywsi/slide.py
pywsi/slide_parser.py
tiler/__init__.py
tiler/ctran.py
tiler/disk_io.py
tiler/exceptions.py
tiler/feature_extractor.py
tiler/filters.py
tiler/lmdb_io.py
tiler/main_parser.py
tiler/rocksdb_io.py
tiler/utilities.py
tiler/wsi_parser.py
tiler/HIPT/__init__.py
tiler/HIPT/HIPT_4K/__init__.py
tiler/HIPT/HIPT_4K/attention_visualization_utils.py
tiler/HIPT/HIPT_4K/hipt_4k.py
tiler/HIPT/HIPT_4K/hipt_heatmap_utils.py
tiler/HIPT/HIPT_4K/hipt_model_utils.py
tiler/HIPT/HIPT_4K/vision_transformer.py
tiler/HIPT/HIPT_4K/vision_transformer4k.py
PySlyde-0.1.0.dist-info/METADATA
PySlyde-0.1.0.dist-info/WHEEL
PySlyde-0.1.0.dist-info/top_level.txt
PySlyde-0.1.0.dist-info/RECORD
