Metadata-Version: 2.1
Name: PySlyde
Version: 0.1.0
Summary: A Python package for preprocessing pathology whole slide images.
Home-page: https://github.com/gregoryverghese/PySlide
Author: Gregory Verghese
Author-email: gregory.verghese@gmail.com
Classifier: Programming Language :: Python :: 3
Classifier: License :: OSI Approved :: MIT License
Classifier: Operating System :: OS Independent
Requires-Python: >=3.12
Requires-Dist: einops
Requires-Dist: h5py
Requires-Dist: huggingface-hub
Requires-Dist: lmdb
Requires-Dist: matplotlib
Requires-Dist: pandas
Requires-Dist: rocksdb
Requires-Dist: scipy
Requires-Dist: seaborn
Requires-Dist: scikit-image
Requires-Dist: tensorflow
Requires-Dist: timm
Requires-Dist: webdataset
